LICENSE
README.md
setup.cfg
setup.py
colab_convert/__init__.py
colab_convert/__main__.py
colab_convert.egg-info/PKG-INFO
colab_convert.egg-info/SOURCES.txt
colab_convert.egg-info/dependency_links.txt
colab_convert.egg-info/entry_points.txt
colab_convert.egg-info/requires.txt
colab_convert.egg-info/top_level.txt
colab_convert/lang/ar_DZ.txt
colab_convert/lang/de_DE.txt
colab_convert/lang/en_US.txt
colab_convert/lang/es_ES.txt
colab_convert/lang/nl_NL.txt