Metadata-Version: 2.1
Name: colab-convert
Version: 2.0.5
Summary: Convert .py files runnable in VSCode/Python or Atom/Hydrogen to jupyter/colab .ipynb notebooks and vice versa
Home-page: https://github.com/MSFTserver/colab-convert
Author: HostsServer
Author-email: msftserver@gmail.com
License: MIT
Keywords: vscode,jupyter,convert,ipynb,py,atom,hydrogen,colab,google,google colab,notebook
Platform: UNKNOWN
License-File: LICENSE
